{
	"header.category": "Filtrar",
	"header.games": "Juegos",
	"header.careers": "Carreras",
	"header.contact": "Contáctenos",
	"categories.genres": "Todo",
	"categories.platform": "Todas las plataformas",
	"categories.match3": "Combina 3",
	"categories.word": "Palabra",
	"categories.merge": "Unir",
	"categories.card": "Tarjeta",
	"categories.puzzle": "Rompecabezas",
	"categories.differences": "Diferencias",
	"footer.privacy": "política de privacidad",
	"footer.terms": "Términos y condiciones",
	"contacts_title": "Contacto",
	"contacts_address": "Calle Eu Tong Sen, 6, Soho 1, 09-09\nSingapur",
	"inquiries_title": "Consultas",
	"inquiries_text": "Para cualquier consulta, pregunta o recomendación, por favor contáctenos a través de esta dirección:",
	"available": "También disponible en:",
	"requirements_header": "Compatible con:",
	"requirements.iOs": "iOS 12.0 y superior",
	"requirements.MacOS": "MacOS 10.9 o posterior",
	"requirements.Android": "6.0 y superiores",
	"requirements.Windows OS": "Windows 10 o superior",
	"other_games": "Juegos que te pueden gustar:",
	"title": "Los mejores juegos HTML-5 que existen",
	"description": "Crear juegos de alta calidad para que todos disfruten",
	"description_title": "Descripción",
	"features_title": "Características:",
	"game_info": "Información del juego",
	"genres.all": "Todo",
	"genres.strategy": "Estrategia",
	"genres.puzzles": "Rompecabezas",
	"genres.match3": "Match3",
	"genres.educational": "Educativo",
	"genres.cards": "Tarjetas",
	"mygames": "Mis juegos",
	"search_placeholder": "Encuentra un juego o género",
	"language": "Idioma",
	"back_button": "Atrás"
}